{
  "data": {
    "Weekday": {
      "title": "Weekday Shuttle",
      "color": "cc66ff",
      "tag": "Weekday",
      "oppositeColor": "000000",
      "max": [
        43.7671699,
        -71.68254
      ],
      "min": [
        43.7576299,
        -71.69064
      ],
      "stops": {
        "PSU Shuttle": [
          "101",
          "102",
          "103",
          "104",
          "105",
          "108",
          "106",
          "107"
        ]
      },
      "scheduledStops": {
        "inbound": [
          "101",
          "1001_ar"
        ]
      },
      "scheduledTimeRange": {
        "Psu Shuttle": {
          "MoTuWeThFr": {
            "first": "07:30:00",
            "last": "23:20:00"
          }
        }
      }
    },
    "Weekend": {
      "title": "Weekend Shuttle",
      "color": "0066ff",
      "tag": "Weekend",
      "oppositeColor": "ffffff",
      "max": [
        43.76896,
        -71.68254
      ],
      "min": [
        43.7576299,
        -71.74149
      ],
      "stops": {
        "PSU Shuttle": [
          "101",
          "102",
          "103",
          "104",
          "105",
          "108",
          "106",
          "107",
          "109",
          "110"
        ]
      },
      "scheduledStops": {
        "inbound": [
          "101",
          "1001_ar"
        ],
        "outbound": [
          "101",
          "1001_ar"
        ]
      },
      "scheduledTimeRange": {
        "Psu Shuttle": {
          "Saturday": {
            "first": "13:00:00",
            "last": "17:18:00"
          },
          "Sunday": {
            "first": "17:00:00",
            "last": "23:20:00"
          }
        }
      }
    }
  },
  "copyright": "All data copyright Plymouth State University 2019."
}