{
  "data": {
    "101": {
      "routes": {},
      "lon": "-71.68254",
      "title": "Ice Arena",
      "stopId": "0101",
      "tag": "101",
      "lat": "43.7586299"
    },
    "102": {
      "routes": {},
      "lon": "-71.68449",
      "title": "ALLWell North",
      "stopId": "0102",
      "tag": "102",
      "lat": "43.7621999"
    },
    "103": {
      "routes": {},
      "lon": "-71.6870799",
      "title": "Temporary Lot 705",
      "stopId": "0103",
      "tag": "103",
      "lat": "43.7671699"
    },
    "104": {
      "routes": {},
      "lon": "-71.6886999",
      "title": "Langdon Woods",
      "stopId": "0104",
      "tag": "104",
      "lat": "43.76483"
    },
    "105": {
      "routes": {},
      "lon": "-71.69064",
      "title": "Merrill Place",
      "stopId": "0105",
      "tag": "105",
      "lat": "43.7621699"
    },
    "106": {
      "routes": {},
      "lon": "-71.6879",
      "title": "Town Hall",
      "stopId": "0106",
      "tag": "106",
      "lat": "43.7581799"
    },
    "107": {
      "routes": {},
      "lon": "-71.6898799",
      "title": "Lamson Library",
      "stopId": "0107",
      "tag": "107",
      "lat": "43.7576299"
    },
    "108": {
      "routes": {},
      "lon": "-71.68968",
      "title": "Prospect Hall",
      "stopId": "0108",
      "tag": "108",
      "lat": "43.76042"
    },
    "109": {
      "routes": {},
      "lon": "-71.74149",
      "title": "Wal-Mart",
      "stopId": "0109",
      "tag": "109",
      "lat": "43.76896"
    },
    "110": {
      "routes": {},
      "lon": "-71.7152699",
      "title": "Hannaford",
      "stopId": "0110",
      "tag": "110",
      "lat": "43.76875"
    }
  },
  "copyright": "All data copyright Plymouth State University 2019."
}