{
  "data": {
    "277": {
      "title": "1 Escalon/Modesto",
      "color": "ffffff",
      "tag": "277",
      "oppositeColor": "000000",
      "max": [
        37.80286,
        -120.98274
      ],
      "min": [
        37.6852699,
        -121.0502999
      ],
      "stops": {
        "Escalon": [
          "21239",
          "21240",
          "21241",
          "21242",
          "9905",
          "9906",
          "9907",
          "9908",
          "9909",
          "12426",
          "9910",
          "9913",
          "9911",
          "9912",
          "9914",
          "29498",
          "21224",
          "21225",
          "21226",
          "21227",
          "21228",
          "21229",
          "9892",
          "21248",
          "21249",
          "794901",
          "794898",
          "794899",
          "794895"
        ],
        "Modesto": [
          "794895",
          "794896",
          "794897",
          "794900",
          "9894",
          "771494",
          "9892",
          "21224",
          "21225",
          "21226",
          "21227",
          "21228",
          "21229",
          "29497",
          "21236",
          "21237",
          "12425",
          "9903",
          "21238",
          "21239"
        ]
      }
    }
  },
  "copyright": "All data copyright Escalon eTrans 2018."
}